xtgbot/__init__.py
xtgbot/bot.py
xtgbot/ext.py
xtgbot/gen.py
xtgbot/tg/__init__.py
xtgbot/tg/base_type.py
xtgbot/tg/session.py
xtgbot/tg/methods/BaseMethod.py
xtgbot/tg/methods/__init__.py
xtgbot/tg/methods/addStickerToSet.py
xtgbot/tg/methods/answerCallbackQuery.py
xtgbot/tg/methods/answerInlineQuery.py
xtgbot/tg/methods/answerPreCheckoutQuery.py
xtgbot/tg/methods/answerShippingQuery.py
xtgbot/tg/methods/answerWebAppQuery.py
xtgbot/tg/methods/approveChatJoinRequest.py
xtgbot/tg/methods/banChatMember.py
xtgbot/tg/methods/banChatSenderChat.py
xtgbot/tg/methods/close.py
xtgbot/tg/methods/closeForumTopic.py
xtgbot/tg/methods/closeGeneralForumTopic.py
xtgbot/tg/methods/convertGiftToStars.py
xtgbot/tg/methods/copyMessage.py
xtgbot/tg/methods/copyMessages.py
xtgbot/tg/methods/createChatInviteLink.py
xtgbot/tg/methods/createChatSubscriptionInviteLink.py
xtgbot/tg/methods/createForumTopic.py
xtgbot/tg/methods/createInvoiceLink.py
xtgbot/tg/methods/createNewStickerSet.py
xtgbot/tg/methods/declineChatJoinRequest.py
xtgbot/tg/methods/deleteBusinessMessages.py
xtgbot/tg/methods/deleteChatPhoto.py
xtgbot/tg/methods/deleteChatStickerSet.py
xtgbot/tg/methods/deleteForumTopic.py
xtgbot/tg/methods/deleteMessage.py
xtgbot/tg/methods/deleteMessages.py
xtgbot/tg/methods/deleteMyCommands.py
xtgbot/tg/methods/deleteStickerFromSet.py
xtgbot/tg/methods/deleteStickerSet.py
xtgbot/tg/methods/deleteStory.py
xtgbot/tg/methods/deleteWebhook.py
xtgbot/tg/methods/editChatInviteLink.py
xtgbot/tg/methods/editChatSubscriptionInviteLink.py
xtgbot/tg/methods/editForumTopic.py
xtgbot/tg/methods/editGeneralForumTopic.py
xtgbot/tg/methods/editMessageCaption.py
xtgbot/tg/methods/editMessageChecklist.py
xtgbot/tg/methods/editMessageLiveLocation.py
xtgbot/tg/methods/editMessageMedia.py
xtgbot/tg/methods/editMessageReplyMarkup.py
xtgbot/tg/methods/editMessageText.py
xtgbot/tg/methods/editStory.py
xtgbot/tg/methods/editUserStarSubscription.py
xtgbot/tg/methods/exportChatInviteLink.py
xtgbot-0.0.6.dist-info/licenses/LICENSE.md
xtgbot-0.0.6.dist-info/METADATA
xtgbot-0.0.6.dist-info/WHEEL
xtgbot-0.0.6.dist-info/top_level.txt
xtgbot-0.0.6.dist-info/RECORD
