Metadata-Version: 2.4
Name: xtgbot
Version: 0.0.6
Summary: Low-level Python library for interacting with the Telegram Bot API
Home-page: https://github.com/vi_is_ramen/xtgbot
Author: Ivan Chetchasov
Author-email: vi.is.chapmann@gmail.com
Classifier: Programming Language :: Python :: 3
Classifier: Operating System :: OS Independent
Requires-Python: >=3.10
License-File: LICENSE.md
Requires-Dist: aiohttp
Dynamic: license-file
